mediaserver_processor/__init__.py
mediaserver_processor/__main__.py
mediaserver_processor/helpers.py
mediaserver_processor/image_processor.py
mediaserver_processor-0.0.5.dist-info/LICENSE
mediaserver_processor-0.0.5.dist-info/METADATA
mediaserver_processor-0.0.5.dist-info/WHEEL
mediaserver_processor-0.0.5.dist-info/entry_points.txt
mediaserver_processor-0.0.5.dist-info/top_level.txt
mediaserver_processor-0.0.5.dist-info/RECORD
