Metadata-Version: 2.1
Name: mediaserver-processor
Version: 0.0.5
Summary: Python script for mediaserver watching, resizing and adding files to a source set.
Home-page: https://github.com/jobveldhuis/python-mediaserver-processor
Author: Job Veldhuis
Author-email: job@baukefrederik.me
License: UNKNOWN
Platform: UNKNOWN
Classifier: Programming Language :: Python :: 3
Classifier: Development Status :: 4 - Beta
Classifier: Intended Audience :: Developers
Classifier: Topic :: Software Development
Classifier: License :: OSI Approved :: MIT License
Classifier: Operating System :: OS Independent
Requires-Python: >=3.6
Requires-Dist: watchgod
Requires-Dist: pillow
Requires-Dist: pyYaml
